QA_OTGBroker/__init__.py
QA_OTGBroker/app.py
QA_OTGBroker/realtime.py
QA_OTGBroker/syscollect.py
QA_OTGBroker/ctpse/LinuxDataCollect64.so
QA_OTGBroker/ctpse/WinDataCollect32.dll
QA_OTGBroker/ctpse/WinDataCollect64.dll
quantaxis_otgbroker-1.9.2.dist-info/LICENSE
quantaxis_otgbroker-1.9.2.dist-info/METADATA
quantaxis_otgbroker-1.9.2.dist-info/WHEEL
quantaxis_otgbroker-1.9.2.dist-info/entry_points.txt
quantaxis_otgbroker-1.9.2.dist-info/top_level.txt
quantaxis_otgbroker-1.9.2.dist-info/zip-safe
quantaxis_otgbroker-1.9.2.dist-info/RECORD
